mcreep/__init__.py
mcreep/const.py
mcreep/fit.py
mcreep/func.py
mcreep/io.py
mcreep/model.py
mcreep-1.1.6.dist-info/LICENCE
mcreep-1.1.6.dist-info/METADATA
mcreep-1.1.6.dist-info/WHEEL
mcreep-1.1.6.dist-info/top_level.txt
mcreep-1.1.6.dist-info/RECORD
