Metadata-Version: 2.1
Name: mcreep
Version: 1.1.6
Summary: Fitting of various pre-defined models to creep data.
Home-page: https://github.com/mirekslouf/mcreep/
Author: Mirek Slouf
Author-email: mirek.slouf@gmail.com
License: MIT
Project-URL: Documentation, https://mirekslouf.github.io/mcreep/
Classifier: Programming Language :: Python :: 3
Classifier: License :: OSI Approved :: MIT License
Classifier: Operating System :: OS Independent
Requires-Python: >=3.6
License-File: LICENCE
